gmine/__init__.py
gmine/__main__.py
gmine/cml.py
gmine/core.py
gmine/regex.py
gmine-0.1.8.dist-info/METADATA
gmine-0.1.8.dist-info/WHEEL
gmine-0.1.8.dist-info/top_level.txt
gmine-0.1.8.dist-info/RECORD
