Metadata-Version: 2.1
Name: gmine
Version: 0.1.8
Summary: Text mining application
Requires-Dist: pandas
